cosmix/__init__.py
cosmix/cosmix.py
cosmix/geant4.py
cosmix/particle.py
cosmix/plotting.py
cosmix/simulation.py
cosmix/util.py
cosmix/landau/MCT.py
cosmix/landau/__init__.py
cosmix/landau/analysis.py
cosmix/landau/fitting_landau.py
cosmix/landau/landau.py
cosmix-0.2.dist-info/LICENSE
cosmix-0.2.dist-info/METADATA
cosmix-0.2.dist-info/WHEEL
cosmix-0.2.dist-info/top_level.txt
cosmix-0.2.dist-info/zip-safe
cosmix-0.2.dist-info/RECORD
