Metadata-Version: 2.1
Name: cosmix
Version: 0.2
Summary: Cosmic ray model for astronomical imaging detectors
Home-page: UNKNOWN
Author: David Lucsanyi
License: MIT License
Project-URL: Source, https://gitlab.com/david.lucsanyi/cosmix
Project-URL: Tracker, https://gitlab.com/david.lucsanyi/cosmix/-/issues
Keywords: cosmic rays
Platform: unix
Platform: linux
Platform: osx
Platform: win32
Classifier: Development Status :: 4 - Beta
Classifier: Intended Audience :: Developers
Classifier: Intended Audience :: Science/Research
Classifier: Topic :: Software Development :: Build Tools
Classifier: Topic :: Scientific/Engineering :: Physics
Classifier: License :: OSI Approved :: MIT License
Classifier: Programming Language :: Python :: 3
Classifier: Programming Language :: Python :: 3.7
Classifier: Programming Language :: Python :: 3.8
Classifier: Programming Language :: Python :: 3.9
Requires-Python: >=3.7
License-File: LICENSE
Requires-Dist: matplotlib
Requires-Dist: numpy
Requires-Dist: pandas
Requires-Dist: scipy
Requires-Dist: tqdm
